whiteboxml/__init__.py
whiteboxml/modeling/__init__.py
whiteboxml/modeling/metrics.py
whiteboxml/processing/__init__.py
whiteboxml/processing/utils.py
whiteboxml-0.0.4.dist-info/LICENSE
whiteboxml-0.0.4.dist-info/METADATA
whiteboxml-0.0.4.dist-info/WHEEL
whiteboxml-0.0.4.dist-info/top_level.txt
whiteboxml-0.0.4.dist-info/RECORD
