Metadata-Version: 2.1
Name: whiteboxml
Version: 0.0.4
Summary: Fancy data functions that will make your life as a data scientist easier.
Home-page: https://github.com/whiteboxml/whiteboxml
Author: WhiteBox
Author-email: info@whiteboxml.com
License: UNKNOWN
Project-URL: Website, https://whiteboxml.com
Platform: UNKNOWN
Classifier: Programming Language :: Python :: 3
Classifier: License :: OSI Approved :: GNU General Public License v3 (GPLv3)
Classifier: Operating System :: OS Independent
Requires-Python: >=3.6
License-File: LICENSE
Requires-Dist: matplotlib
Requires-Dist: scikit-learn
Requires-Dist: seaborn
Requires-Dist: setuptools
Requires-Dist: wheel
